amino_dorks_fix-3.9.8.13.dist-info/licenses/LICENSE
aminodorksfix/__init__.py
aminodorksfix/acm.py
aminodorksfix/client.py
aminodorksfix/constants.py
aminodorksfix/socket.py
aminodorksfix/sub_client.py
aminodorksfix/asyncfix/__init__.py
aminodorksfix/asyncfix/acm.py
aminodorksfix/asyncfix/client.py
aminodorksfix/asyncfix/socket.py
aminodorksfix/asyncfix/sub_client.py
aminodorksfix/lib/__init__.py
aminodorksfix/lib/util/__init__.py
aminodorksfix/lib/util/enums.py
aminodorksfix/lib/util/exceptions.py
aminodorksfix/lib/util/headers.py
aminodorksfix/lib/util/helpers.py
aminodorksfix/lib/util/models.py
aminodorksfix/lib/util/objects.py
amino_dorks_fix-3.9.8.13.dist-info/METADATA
amino_dorks_fix-3.9.8.13.dist-info/WHEEL
amino_dorks_fix-3.9.8.13.dist-info/top_level.txt
amino_dorks_fix-3.9.8.13.dist-info/RECORD
