Metadata-Version: 2.4
Name: amino.dorks.fix
Version: 3.9.8.13
Summary: Library for Amino. Telegram - https://t.me/aminodorks
Home-page: https://github.com/misterio060/amino.dorks.fix
Author: misterio
Author-email: misterio1234321@gmail.com
License: MIT
Keywords: aminoapps,amino.fix,amino,aminodorks,amino-bot,narvii,api,python,python3,python3.x,misterio060
Requires-Python: >=3.10
License-File: LICENSE
Requires-Dist: requests
Requires-Dist: websocket-client==1.3.1
Requires-Dist: setuptools
Requires-Dist: json_minify
Requires-Dist: six
Requires-Dist: aiohttp
Requires-Dist: websockets
Dynamic: author
Dynamic: author-email
Dynamic: description
Dynamic: description-content-type
Dynamic: home-page
Dynamic: keywords
Dynamic: license
Dynamic: license-file
Dynamic: requires-dist
Dynamic: requires-python
Dynamic: summary
